{
  "hash": "808d5c0a",
  "configHash": "a138ef93",
  "lockfileHash": "b0d59d03",
  "browserHash": "5916f97d",
  "optimized": {
    "react-dom/client": {
      "src": "../../node_modules/react-dom/client.js",
      "file": "react-dom_client.js",
      "fileHash": "01bf2a3d",
      "needsInterop": true
    },
    "react": {
      "src": "../../node_modules/react/index.js",
      "file": "react.js",
      "fileHash": "27bdd522",
      "needsInterop": true
    },
    "react/jsx-dev-runtime": {
      "src": "../../node_modules/react/jsx-dev-runtime.js",
      "file": "react_jsx-dev-runtime.js",
      "fileHash": "fb39a9be",
      "needsInterop": true
    }
  },
  "chunks": {
    "react-Na5-BvaJ": {
      "file": "react-Na5-BvaJ.js",
      "isDynamicEntry": false
    }
  }
}